greencell_client/__init__.py
greencell_client/_version.py
greencell_client/access.py
greencell_client/elec_data.py
greencell_client/mqtt_parser.py
greencell_client/state.py
greencell_client/utils.py
greencell_client-1.0.3.dist-info/licenses/LICENSE
greencell_client-1.0.3.dist-info/METADATA
greencell_client-1.0.3.dist-info/WHEEL
greencell_client-1.0.3.dist-info/top_level.txt
greencell_client-1.0.3.dist-info/RECORD
